osmosis_proto/__init__.py
osmosis_proto/cosmos/__init__.py
osmosis_proto/cosmos/auth/__init__.py
osmosis_proto/cosmos/auth/v1beta1/__init__.py
osmosis_proto/cosmos/authz/__init__.py
osmosis_proto/cosmos/authz/v1beta1/__init__.py
osmosis_proto/cosmos/bank/__init__.py
osmosis_proto/cosmos/bank/v1beta1/__init__.py
osmosis_proto/cosmos/base/__init__.py
osmosis_proto/cosmos/base/abci/__init__.py
osmosis_proto/cosmos/base/abci/v1beta1/__init__.py
osmosis_proto/cosmos/base/kv/__init__.py
osmosis_proto/cosmos/base/kv/v1beta1/__init__.py
osmosis_proto/cosmos/base/query/__init__.py
osmosis_proto/cosmos/base/query/v1beta1/__init__.py
osmosis_proto/cosmos/base/reflection/__init__.py
osmosis_proto/cosmos/base/reflection/v1beta1/__init__.py
osmosis_proto/cosmos/base/reflection/v2alpha1/__init__.py
osmosis_proto/cosmos/base/snapshots/__init__.py
osmosis_proto/cosmos/base/snapshots/v1beta1/__init__.py
osmosis_proto/cosmos/base/store/__init__.py
osmosis_proto/cosmos/base/store/v1beta1/__init__.py
osmosis_proto/cosmos/base/tendermint/__init__.py
osmosis_proto/cosmos/base/tendermint/v1beta1/__init__.py
osmosis_proto/cosmos/base/v1beta1/__init__.py
osmosis_proto/cosmos/capability/__init__.py
osmosis_proto/cosmos/capability/v1beta1/__init__.py
osmosis_proto/cosmos/crisis/__init__.py
osmosis_proto/cosmos/crisis/v1beta1/__init__.py
osmosis_proto/cosmos/crypto/__init__.py
osmosis_proto/cosmos/crypto/ed25519/__init__.py
osmosis_proto/cosmos/crypto/multisig/__init__.py
osmosis_proto/cosmos/crypto/multisig/v1beta1/__init__.py
osmosis_proto/cosmos/crypto/secp256k1/__init__.py
osmosis_proto/cosmos/crypto/secp256r1/__init__.py
osmosis_proto/cosmos/distribution/__init__.py
osmosis_proto/cosmos/distribution/v1beta1/__init__.py
osmosis_proto/cosmos/evidence/__init__.py
osmosis_proto/cosmos/evidence/v1beta1/__init__.py
osmosis_proto/cosmos/feegrant/__init__.py
osmosis_proto/cosmos/feegrant/v1beta1/__init__.py
osmosis_proto/cosmos/genutil/__init__.py
osmosis_proto/cosmos/genutil/v1beta1/__init__.py
cosmos_proto-0.0.0.dist-info/WHEEL
cosmos_proto-0.0.0.dist-info/METADATA
cosmos_proto-0.0.0.dist-info/RECORD
