Metadata-Version: 2.1
Name: cosmos-proto
Version: 0.0.0
Summary: The Python Protobuf implementation for Cosmos SDK chains
Home-page: https://github.com/AstroTech-Labs/cosmos_proto
License: MIT
Keywords: jigu,blockchain,cosmos,defi,crypto
Author: AstroTech Labs, PTE.
Author-email: buidl@astrotechlabs.com
Requires-Python: >=3.7,<4.0
Classifier: Intended Audience :: Developers
Classifier: License :: OSI Approved :: MIT License
Classifier: Natural Language :: English
Classifier: Programming Language :: Python :: 3
Classifier: Programming Language :: Python :: 3.7
Classifier: Programming Language :: Python :: 3.8
Classifier: Programming Language :: Python :: 3.9
Classifier: Programming Language :: Python :: 3.10
Classifier: Programming Language :: Python :: 3
Classifier: Programming Language :: Python :: 3.10
Classifier: Programming Language :: Python :: 3.7
Classifier: Programming Language :: Python :: 3.8
Classifier: Programming Language :: Python :: 3.9
Requires-Dist: MarkupSafe (==2.0.1)
Requires-Dist: betterproto (==2.0.0b4)
Project-URL: Repository, https://github.com/AstroTech-Labs/cosmos_proto
